mcp/README.md
mcp/requirements.txt
mcp/server.py
skill_jangler/__init__.py
skill_jangler-0.1.0.dist-info/METADATA
skill_jangler-0.1.0.dist-info/WHEEL
skill_jangler-0.1.0.dist-info/entry_points.txt
skill_jangler-0.1.0.dist-info/licenses/LICENSE
skill_jangler-0.1.0.dist-info/RECORD
