Metadata-Version: 2.4
Name: skill-jangler
Version: 0.1.0
Summary: Scrape and index API docs as claude skills with gusto
Author-email: Jarad DeLorenzo <jaradd@gmail.com>
License-File: LICENSE
Requires-Python: >=3.12
Requires-Dist: beautifulsoup4>=4.12.0
Requires-Dist: mcp>=1.0.0
Requires-Dist: requests>=2.31.0
